runtest/__init__.py
runtest/check.py
runtest/cli.py
runtest/copy.py
runtest/exceptions.py
runtest/extract.py
runtest/filter_api.py
runtest/filter_constructor.py
runtest/run.py
runtest/scissors.py
runtest/tuple_comparison.py
runtest/version.py
runtest/test/__init__.py
runtest/test/different_length/out.txt
runtest/test/different_length/ref.txt
runtest/test/generic/out.txt
runtest/test/generic/ref.txt
runtest/test/ignore_order/out.txt
runtest/test/ignore_order/ref.txt
runtest/test/ignore_order_and_sign/out.txt
runtest/test/ignore_order_and_sign/ref.txt
runtest/test/integers/out.txt
runtest/test/integers/ref.txt
runtest/test/only_string/out.txt
runtest/test/only_string/ref.txt
runtest-2.3.5.dist-info/WHEEL
runtest-2.3.5.dist-info/METADATA
runtest-2.3.5.dist-info/RECORD
