Metadata-Version: 2.4
Name: runtest
Version: 2.3.5
Summary: runtest: Numerically tolerant end-to-end test library for research software.
Home-page: https://github.com/bast/runtest
Author: Radovan Bast
Author-email: radovan.bast@uit.no
Classifier: License :: OSI Approved :: Mozilla Public License 2.0 (MPL 2.0)
